ratelimit/__init__.py
ratelimit/core.py
ratelimit/decorators.py
ratelimit/exceptions.py
ratelimit/middleware.py
ratelimit/mixins.py
ratelimit/models.py
ratelimit/tests.py
ratelimit/utils.py
django_ratelimit-3.0.0.dist-info/LICENSE
django_ratelimit-3.0.0.dist-info/METADATA
django_ratelimit-3.0.0.dist-info/WHEEL
django_ratelimit-3.0.0.dist-info/top_level.txt
django_ratelimit-3.0.0.dist-info/RECORD
